arger/__init__.py
arger/__version__.py
arger/docstring.py
arger/main.py
arger/typing_utils.py
arger-2.1.0.dist-info/WHEEL
arger-2.1.0.dist-info/METADATA
arger-2.1.0.dist-info/licenses/LICENSE.md
arger-2.1.0.dist-info/RECORD
