Metadata-Version: 2.1
Name: arger
Version: 2.1.0
Summary: Create argparser automatically from function signatures
License: MIT
Author-email: Noortheen Raja <jnoortheen@gmail.com>
Requires-Python: >=3.10
Classifier: Development Status :: 1 - Planning
Classifier: Environment :: Console
Classifier: Intended Audience :: Developers
Classifier: License :: Freely Distributable
Classifier: Natural Language :: English
Classifier: Operating System :: OS Independent
Classifier: Programming Language :: Python
Classifier: Programming Language :: Python :: 3
Classifier: Programming Language :: Python :: 3 :: Only
Provides-Extra: doc
Requires-Dist: mkdocs; extra == "doc"
Requires-Dist: mkdocs-material; extra == "doc"
Requires-Dist: mkdocstrings; extra == "doc"
Requires-Dist: pytkdocs; extra == "doc"
Requires-Dist: mknotebooks; extra == "doc"
Requires-Dist: pymdown-extensions; extra == "doc"
Requires-Dist: pygments; extra == "doc"
Provides-Extra: test
Requires-Dist: pytest; extra == "test"
Requires-Dist: pytest-cov; extra == "test"
Requires-Dist: pytest-describe; extra == "test"
Requires-Dist: pytest-expecter; extra == "test"
Requires-Dist: pytest-random; extra == "test"
Requires-Dist: freezegun; extra == "test"
Requires-Dist: pytest-lazy-fixtures; extra == "test"
Requires-Dist: nbformat; extra == "test"
Requires-Dist: ruff; extra == "test"
Requires-Dist: mypy; extra == "test"
Project-URL: documentation, https://arger.readthedocs.io
Project-URL: homepage, https://pypi.org/project/arger
Project-URL: repository, https://github.com/jnoortheen/arger
